LICENSE
MANIFEST.in
README.rst
requirements.txt
setup.py
bo/__init__.py
bo/main.py
bo.egg-info/PKG-INFO
bo.egg-info/SOURCES.txt
bo.egg-info/dependency_links.txt
bo.egg-info/entry_points.txt
bo.egg-info/requires.txt
bo.egg-info/top_level.txt
bo/core/__init__.py
bo/core/brain.py
bo/core/connectors.py
bo/core/plugins.py
bo/dispatch/__init__.py
bo/dispatch/dispatcher.py
bo/dispatch/saferef.py
bo/dist/__init__.py
bo/dist/connectors/__init__.py
bo/dist/connectors/console.py
bo/dist/connectors/xmpp.py
bo/dist/plugins/__init__.py
bo/dist/plugins/echo.py
bo/dist/plugins/rand.py
bo/dist/plugins/uptime.py