Metadata-Version: 1.1
Name: bo
Version: 0.1-alpha
Summary: A simple, multi-protocol, extendable and embeddable chatbot
Home-page: http://bitbucket.org/konikos/bo
Author: Nikos Kokolakis
Author-email: kokolakisnikos@gmail.com
License: BSD style, see the included LICENSE file for details
Platform: UNKNOWN
Classifier: Programming Language :: Python
Classifier: License :: OSI Approved :: BSD License
Classifier: Topic :: Communications
